[
    {
        "name": "Борщ",
        "ingredients": [
            "буряк - 2 шт",
            "морква - 1 шт",
            "картопля - 3 шт",
            "капуста - 300 г",
            "цибуля - 1 шт",
            "томати - 2 шт",
            "часник - 2 зубчики",
            "м'ясо (свинина чи яловичина) - 300 г",
            "олія - 2 ст. ложки",
            "вода - 2 л",
            "сіль - за смаком",
            "лавровий лист - 2 шт"
        ],
        "instructions": "1️⃣ Варити м'ясо до готовності, дістати з бульйону та нарізати.\n2️⃣ Нарізати буряк, моркву та цибулю, обсмажити на олії.\n3️⃣ Додати нарізані томати або томатну пасту до смажених овочів.\n4️⃣ У бульйон додати картоплю, варити до напівготовності.\n5️⃣ Додати капусту, обсмажені овочі та м'ясо.\n6️⃣ Приправити сіллю, часником, лавровим листом та варити ще 10 хвилин.",
        "image": "https://i.obozrevatel.com/food/recipemain/2019/3/4/3c4d2ecd-df43-41d2-a17a-71914ead0e50w1023r1s.jpg"
    },
    {
        "name": "Олів'є",
        "ingredients": [
            "картопля - 3 шт",
            "морква - 1 шт",
            "яйця - 4 шт",
            "ковбаса варена - 300 г",
            "горошок консервований - 1 банка",
            "солоні огірки - 2 шт",
            "майонез - за смаком",
            "сіль - за смаком"
        ],
        "instructions": "1️⃣ Відварити картоплю, моркву та яйця, охолодити.\n2️⃣ Нарізати всі інгредієнти кубиками однакового розміру.\n3️⃣ Змішати все у великій мисці, додати горошок.\n4️⃣ Заправити майонезом, посолити за смаком і перемішати.",
        "image": "https://retsepty.in.ua/wp-content/uploads/2023/07/image-2023-07-17T131313.035.jpg"
    },
    {
        "name": "Плов",
        "ingredients": [
            "рис - 500 г",
            "м'ясо (баранина або свинина) - 400 г",
            "морква - 3 шт",
            "цибуля - 2 шт",
            "олія - 3 ст. ложки",
            "часник - 1 головка",
            "сіль - за смаком",
            "спеції для плову - за смаком"
        ],
        "instructions": "1️⃣ Нарізати м'ясо невеликими шматочками, обсмажити до рум'яної скоринки.\n2️⃣ Додати нарізану цибулю та моркву, обсмажити разом 5-7 хвилин.\n3️⃣ Додати промитий рис, рівномірно розподілити.\n4️⃣ Вставити часник у рис, залити водою, щоб вона покрила рис на 2 см.\n5️⃣ Варити на слабкому вогні під кришкою, поки рис не приготується.",
        "image": "https://encrypted-tbn0.gstatic.com/images?q=tbn:ANd9GcRhuI9qiwRTbKf1a3yPB0l6PqmsxlBsbOM1Fg&s"
    },
    {
        "name": "Вареники з картоплею",
        "ingredients": [
            "борошно - 500 г",
            "вода - 200 мл",
            "яйце - 1 шт",
            "сіль - 1 ч. ложка",
            "картопля - 500 г",
            "цибуля - 1 шт",
            "олія - 2 ст. ложки"
        ],
        "instructions": "1️⃣ Змішати борошно, яйце, воду та сіль, замісити тісто, залишити на 20 хвилин.\n2️⃣ Відварити картоплю, розім'яти в пюре, додати смажену цибулю.\n3️⃣ Розкатати тісто, вирізати кружечки.\n4️⃣ Покласти начинку, зліпити вареники.\n5️⃣ Відварити у підсоленій воді до готовності.",
        "image": "https://i.obozrevatel.com/food/recipemain/2019/1/5/f9198520-36d3-4388-8a4d-b6af1646cec31.jpg?size=636x424"
    },
    {
        "name": "Млинці",
        "ingredients": [
            "борошно - 250 г",
            "молоко - 500 мл",
            "яйця - 2 шт",
            "цукор - 1 ст. ложка",
            "сіль - 0.5 ч. ложки",
            "олія - 2 ст. ложки"
        ],
        "instructions": "1️⃣ Змішати яйця, цукор і сіль.\n2️⃣ Додати молоко та поступово вводити борошно, добре перемішуючи.\n3️⃣ Додати олію, залишити тісто на 15 хвилин.\n4️⃣ Смажити млинці на розігрітій сковороді до золотистого кольору.",
        "image": "https://yasensvit.ua/uploads/recipes/prev/6384b279a98d9.jpg"
    },
    {
        "name": "Голубці",
        "ingredients": [
            "капуста - 1 качан",
            "фарш м'ясний - 500 г",
            "рис - 150 г",
            "морква - 1 шт",
            "цибуля - 1 шт",
            "томатна паста - 2 ст. ложки",
            "олія - 2 ст. ложки",
            "сіль - за смаком",
            "перець - за смаком"
        ],
        "instructions": "1️⃣ Відварити капусту, відокремити листя.\n2️⃣ Змішати фарш, відварений рис, сіль і перець.\n3️⃣ Загорнути начинку в капустяне листя.\n4️⃣ Обсмажити моркву та цибулю, додати томатну пасту.\n5️⃣ Викласти голубці у каструлю, залити водою з піджаркою. Тушкувати 40-50 хвилин.",
        "image": "https://food.net.ua/uploads/posts/2023-06/golubcy-klassicheskie-v-kastrule_1615212389_17_max.jpg"
    },
    {
        "name": "Котлети по-київськи",
        "ingredients": [
            "куряче філе - 2 шт",
            "масло вершкове - 50 г",
            "зелень (петрушка, кріп) - 20 г",
            "борошно - 2 ст. ложки",
            "яйце - 1 шт",
            "панірувальні сухарі - 100 г",
            "олія для смаження - за потребою",
            "сіль, перець - за смаком"
        ],
        "instructions": "1️⃣ Відбити куряче філе, посолити і поперчити.\n2️⃣ Змішати масло із зеленню, сформувати рулетик і загорнути його у філе.\n3️⃣ Обкачати в борошні, яйці та сухарях, повторити двічі.\n4️⃣ Обсмажити до золотистої скоринки, потім доготувати у духовці 10-15 хвилин.",
        "image": "https://images.unian.net/photos/2020_11/thumb_files/400_0_1605701419-4898.jpg?0.07469344447636028"
    },
    {
        "name": "Сирники",
        "ingredients": [
            "сир (творог) - 500 г",
            "борошно - 3 ст. ложки",
            "яйце - 1 шт",
            "цукор - 2 ст. ложки",
            "ванілін - за смаком",
            "олія - 2 ст. ложки"
        ],
        "instructions": "1️⃣ Змішати сир, яйце, цукор, ванілін та борошно.\n2️⃣ Сформувати сирники, обкачати у борошні.\n3️⃣ Смажити на олії до золотистого кольору з обох боків.",
        "image": "https://www.gurmania.com.ua/wp-content/uploads/2024/01/recept-syrnykiv.jpg"
    },
    {
        "name": "Кекс з родзинками",
        "ingredients": [
            "вершкове масло - 150 г",
            " яйця - 3 шт.",
            "цукор - 150 г",
            "родзинки- 150 г",
            "борошно - 200 г",
            "Сіль - 0,5 ч. л.",
            "розпушувач - 1 ст. л. Цукор (Ванільний) - 10 г",
            "Олія для змащування форми - 1 ст. л.",
            "Цукрова пудра для посипання - 2 ст. л."
        ],
        "instructions": "1️⃣ Підготувати інгредієнти. Родзинки залити окропом на 5 хв, обсушити та змішати з 1 ст. л. борошна.\n2️⃣ Просіяти борошно з розпушувачем. Масло збити з цукром, сіллю та ванільним цукром. По одному додати яйця, збиваючи після кожного.\n3️⃣ Поступово додати борошно, перемішати, потім додати родзинки.\n4️⃣ Форму змастити олією, викласти тісто, випікати при 170°C 60-80 хв. Перевірити готовність шпажкою. Готовий кекс посипати цукровою пудрою. Смачного!",
        "image": "https://encrypted-tbn0.gstatic.com/images?q=tbn:ANd9GcSmAGhV73TyRhg1yxc7i6tYWn6b5EYlvaR-HQ&s"
    },
    {
        "name": "Салат з крабовими паличками",
        "ingredients": [
            "крабові палички - 250 г",
            "кукурудза(консервована) - банка",
            "яйця - 3 шт.",
            "огірок - 1 шт.",
            "рис - 0,5 склянки",
            "цибуля - половина (можна взагалі не додавати",
            "якщо ви не любитель цибулі)",
            "майонез - за смаком",
            "сіль - за смаком",
            "перець - за смаком."
        ],
        "instructions": "1️⃣ Варимо яйця та рис, потім їх потрібно остудити до кімнатної температури. Рис промити.\n2️⃣ Нарізаємо холодні крабові палички та яйця маленькими кубиками.\n3️⃣ Огірок та цибулю миємо, другий також нарізаємо кубиками, цибулю - дрібно.\n4️⃣ Зливаємо рідину з кукурудзи, можна відкинути на сито.\n5️⃣ З'єднуємо всі інгредієнти в салатниці, додаємо сіль, перець і майонез за смаком.",
        "image": "https://novograd.city/upload/article/o_1epoap3cnkol14k2vm31vh2lh85c.jpg"
    }
]